pythonenv/__init__.py
pythonenv/package_metadata.json
pythonenv-0.0.34.data/scripts/python_shebang
pythonenv-0.0.34.dist-info/DESCRIPTION.rst
pythonenv-0.0.34.dist-info/METADATA
pythonenv-0.0.34.dist-info/metadata.json
pythonenv-0.0.34.dist-info/RECORD
pythonenv-0.0.34.dist-info/top_level.txt
pythonenv-0.0.34.dist-info/WHEEL
