Metadata-Version: 2.0
Name: pythonenv
Version: 0.0.34
Summary: find a compatible python interpreter for a script
Home-page: https://github.com/yahoo/python_shebang
Author: dhubbard
Author-email: dhubbard@yahoo-inc.com
License: Apache V2
Keywords: shebang hashbang
Platform: UNKNOWN
Classifier: Topic :: Utilities
